{
  "nodes":
  [
    {
      "name":"euler"
      , "id":3085699464
      , "type":"component"
      , "children":
      [
        {
          "name":"Stream Read"
          , "id":3085727336
          , "details":
          [
            {
              "type":"table"
              , "Basic Block":"euler.B1.start"
              , "Width":"32 bits"
              , "Depth":"0"
              , "Stall-free":"No"
              , "Latency":"0"
            }
          ]
          , "debug":
          [
            [
              {
                "filename":"euler/euler.c"
                , "line":19
              }
            ]
          ]
          , "type":"inst"
        }
        , {
          "name":"Stream Write"
          , "id":3085783256
          , "details":
          [
            {
              "type":"table"
              , "Basic Block":"euler.B2"
              , "Width":"64 bits"
              , "Depth":"0"
              , "Stall-free":"No"
              , "Latency":"0"
            }
          ]
          , "debug":
          [
            [
              {
                "filename":"euler/euler.c"
                , "line":26
              }
            ]
          ]
          , "type":"inst"
        }
      ]
    }
    , {
      "name":"return.euler"
      , "id":3085537992
      , "details":
      [
        {
          "type":"table"
          , "Width":"64 bits"
          , "Depth":"0"
          , "Ready Latency":"0"
          , "Bits per Symbol":"64 bits"
          , "Uses Packets":"No"
          , "Uses Ready":"Yes"
          , "Uses Empty":"No"
          , "First symbol in high order bits":"No"
        }
      ]
      , "type":"stream"
    }
    , {
      "name":"call.euler"
      , "id":3085698312
      , "details":
      [
        {
          "type":"table"
          , "Width":"32 bits"
          , "Depth":"0"
          , "Reday Latency":"0"
          , "Bits per Symbol":"32 bits"
          , "Uses Packets":"No"
          , "Uses Valid":"Yes"
          , "Uses Empty":"No"
          , "First symbol in high order bits":"No"
        }
      ]
      , "type":"stream"
    }
  ]
  , "links":
  [
    {
      "from":3085783256
      , "to":3085537992
    }
    , {
      "from":3085698312
      , "to":3085727336
    }
    , {
      "from":3085727336
      , "to":3085783256
    }
  ]
}
