<?xml version="1.0" encoding="utf-8"?>
<Messages>
	<Message severity="INFO" prefix="[SCHED 204-61]" key="SCHED_PIPELINING_STATUS_631" tag="SCHEDULE" content="Option &apos;relax_ii_for_timing&apos; is enabled, will increase II to preserve clock frequency constraints."/>
	<Message severity="INFO" prefix="[HLS 200-10]" key="HLS_10_1312" tag="" content="Analyzing design file &apos;extr_.nginxsrccorengx_parse_time.c_ngx_parse_http_time_with_main.c&apos; ..."/>
	<Message severity="INFO" prefix="[HLS 200-111]" key="HLS_111_965" tag="" content="Finished Linking Time (s): cpu = 00:02:06 ; elapsed = 00:13:24 . Memory (MB): peak = 832.453 ; gain = 132.133 ; free physical = 14263 ; free virtual = 43767"/>
	<Message severity="INFO" prefix="[HLS 200-111]" key="HLS_111_965" tag="" content="Finished Checking Pragmas Time (s): cpu = 00:02:06 ; elapsed = 00:13:24 . Memory (MB): peak = 832.453 ; gain = 132.133 ; free physical = 14263 ; free virtual = 43767"/>
	<Message severity="INFO" prefix="[HLS 200-10]" key="HLS_10_1467" tag="" content="Starting code transformations ..."/>
	<Message severity="INFO" prefix="[HLS 200-111]" key="HLS_111_965" tag="" content="Finished Standard Transforms Time (s): cpu = 00:02:07 ; elapsed = 00:13:26 . Memory (MB): peak = 832.453 ; gain = 132.133 ; free physical = 14264 ; free virtual = 43768"/>
	<Message severity="INFO" prefix="[HLS 200-10]" key="HLS_10_1472" tag="" content="Checking synthesizability ..."/>
	<Message severity="ERROR" prefix="[SYNCHK 200-61]" key="SYNCHK_ARRAY_UNKNOWN_SIZE_354" tag="" content="extr_.nginxsrccorengx_parse_time.c_ngx_parse_http_time_with_main.c:44: unsupported memory access on variable &apos;value&apos; which is (or contains) an array with unknown size at compile time."/>
	<Message severity="INFO" prefix="[SYNCHK 200-10]" key="SYNCHK_SYNCHK_SUMMARY_377" tag="" content="1 error(s), 0 warning(s)."/>
	<Message severity="ERROR" prefix="[HLS 200-70]" key="HLS_70_1855" tag="" content="Synthesizability check failed."/>
	<Message severity="INFO" prefix="[HLS 200-10]" key="HLS_10_1303" tag="" content="Opening project &apos;/home/vivado/HLStools/vivado/214_revisao/proj_extr_.numpynumpylinalglapack_litef2c_c_lapack.c_claswp__with_main.c&apos;."/>
</Messages>
